ark_sdk_python/__init__.py
ark_sdk_python/actions/__init__.py
ark_sdk_python/actions/ark_action.py
ark_sdk_python/actions/ark_cache_action.py
ark_sdk_python/actions/ark_configure_action.py
ark_sdk_python/actions/ark_exec_action.py
ark_sdk_python/actions/ark_login_action.py
ark_sdk_python/actions/ark_profiles_action.py
ark_sdk_python/actions/ark_service_exec_action.py
ark_sdk_python/args/__init__.py
ark_sdk_python/args/ark_args_formatter.py
ark_sdk_python/args/ark_pydantic_argparse.py
ark_sdk_python/ark.py
ark_sdk_python/ark_api.py
ark_sdk_python/auth/__init__.py
ark_sdk_python/auth/ark_auth.py
ark_sdk_python/auth/ark_isp_auth.py
ark_sdk_python/auth/identity/__init__.py
ark_sdk_python/auth/identity/ark_identity.py
ark_sdk_python/auth/identity/ark_identity_fqdn_resolver.py
ark_sdk_python/auth/identity/ark_identity_service_user.py
ark_sdk_python/cli_services/__init__.py
ark_sdk_python/cli_services/ark_cli_api.py
ark_sdk_python/cli_services/sia/__init__.py
ark_sdk_python/cli_services/sia/common/__init__.py
ark_sdk_python/cli_services/sia/common/ark_sia_base_policies_editor_service.py
ark_sdk_python/cli_services/sia/db/__init__.py
ark_sdk_python/cli_services/sia/db/ark_sia_db_policies_editor_service.py
ark_sdk_python/cli_services/sia/vm/__init__.py
ark_sdk_python/cli_services/sia/vm/ark_sia_vm_policies_editor_service.py
ark_sdk_python/common/__init__.py
ark_sdk_python/common/ark_async_client.py
ark_sdk_python/common/ark_async_request.py
ark_sdk_python/common/ark_client.py
ark_sdk_python/common/ark_ip_utils.py
ark_sdk_python/common/ark_jwt_utils.py
ark_sdk_python/common/ark_keyring.py
ark_sdk_python/common/ark_logger.py
ark_sdk_python/common/ark_page.py
ark_sdk_python/common/ark_pollers.py
ark_sdk_python/common/ark_random_utils.py
ark_sdk_python/common/ark_retry.py
ark_sdk_python/common/ark_system_config.py
ark_sdk_python/common/ark_user_agent.py
ark_sdk_python/common/ark_version.py
ark_sdk_python/common/connections/__init__.py
ark_sdk_python-2.1.4.dist-info/METADATA
ark_sdk_python-2.1.4.dist-info/WHEEL
ark_sdk_python-2.1.4.dist-info/entry_points.txt
ark_sdk_python-2.1.4.dist-info/licenses/LICENSE.txt
ark_sdk_python-2.1.4.dist-info/licenses/NOTICES.md
ark_sdk_python-2.1.4.dist-info/RECORD
