Metadata-Version: 2.4
Name: ark-sdk-python
Version: 2.1.4
Summary: Official Ark SDK / CLI for CyberArk Identity Security Platform
License: Apache-2.0
License-File: LICENSE.txt
License-File: NOTICES.md
Author: CyberArk
Author-email: cyberark@cyberark.com
Requires-Python: >=3.11,<4.0
Classifier: Intended Audience :: Developers
Classifier: License :: OSI Approved :: Apache Software License
Classifier: Natural Language :: English
Classifier: Programming Language :: Python
Classifier: Programming Language :: Python :: 3
Classifier: Programming Language :: Python :: 3.11
Classifier: Programming Language :: Python :: 3.12
Classifier: Programming Language :: Python :: 3.13
Classifier: Programming Language :: Python :: 3.14
Requires-Dist: aenum
Requires-Dist: argcomplete
Requires-Dist: cachetools
Requires-Dist: colorama
Requires-Dist: deepdiff (==8.*)
Requires-Dist: dill
Requires-Dist: fake-useragent (==1.5.1)
Requires-Dist: inquirer
Requires-Dist: keyring
Requires-Dist: keyrings.cryptfile
Requires-Dist: overrides
Requires-Dist: packaging
Requires-Dist: paramiko
Requires-Dist: pexpect ; sys_platform != "win32"
Requires-Dist: progress
Requires-Dist: pycryptodome
Requires-Dist: pydantic (==2.*)
Requires-Dist: pyhumps
Requires-Dist: pyjwt
Requires-Dist: python-dateutil
Requires-Dist: pywinpty ; sys_platform == "win32"
Requires-Dist: pywinrm
Requires-Dist: pyyaml
Requires-Dist: requests
Requires-Dist: tzlocal
Requires-Dist: urlextract
Project-URL: Repository, https://github.com/cyberark/ark-sdk-python
